LICENSE
MANIFEST.in
README.md
requirements.txt
setup.cfg
setup.py
lantern/__init__.py
lantern/color.py
lantern/light.py
yn_lantern.egg-info/PKG-INFO
yn_lantern.egg-info/SOURCES.txt
yn_lantern.egg-info/dependency_links.txt
yn_lantern.egg-info/requires.txt
yn_lantern.egg-info/top_level.txt