Metadata-Version: 1.0
Name: yn-lantern
Version: 1.0.0
Summary: A library for communicating with Yongnuo LED video lights.
Home-page: https://github.com/kenkeiter/lantern
Author: Ken Keiter
Author-email: ken@kenkeiter.com
License: MIT
Platform: UNKNOWN
